README
eveapi.py
setup.py
eveapi.egg-info/PKG-INFO
eveapi.egg-info/SOURCES.txt
eveapi.egg-info/dependency_links.txt
eveapi.egg-info/requires.txt
eveapi.egg-info/top_level.txt
eveapi.egg-info/zip-safe